nimocr/__init__.py
nimocr/annotator.py
nimocr/model/__init__.py
nimocr/model/image_list.py
nimocr/presenter/__init__.py
nimocr/presenter/presenter.py
nimocr/view/__init__.py
nimocr/view/dialog.py
nimocr/view/main_window.py
nimocr/view/widget.py
nimocr-0.1.2.dist-info/METADATA
nimocr-0.1.2.dist-info/WHEEL
nimocr-0.1.2.dist-info/entry_points.txt
nimocr-0.1.2.dist-info/top_level.txt
nimocr-0.1.2.dist-info/RECORD
